mlaut/__init__.py
mlaut/model_selection.py
mlaut/benchmarking/__init__.py
mlaut/benchmarking/base.py
mlaut/benchmarking/evaluation.py
mlaut/benchmarking/metrics.py
mlaut/benchmarking/orchestration.py
mlaut/benchmarking/data/__init__.py
mlaut/benchmarking/data/_base.py
mlaut/benchmarking/data/_hdd.py
mlaut/benchmarking/data/_ram.py
mlaut/benchmarking/results/__init__.py
mlaut/benchmarking/results/_base.py
mlaut/benchmarking/results/_hdd.py
mlaut/benchmarking/results/_ram.py
mlaut/highlevel/strategies.py
mlaut/highlevel/tasks.py
mlaut/resampling/__init__.py
mlaut/resampling/single_split.py
mlaut/shared/__init__.py
mlaut/shared/exceptions.py
mlaut/shared/static_variables.py
mlaut/strategies/baseline.py
mlaut/strategies/bayes.py
mlaut/strategies/cluster.py
mlaut/strategies/decision_trees.py
mlaut/strategies/ensemble.py
mlaut/strategies/glm.py
mlaut/strategies/neural_networks.py
mlaut/strategies/svm.py
mlaut-0.2.0.dist-info/AUTHORS.rst
mlaut-0.2.0.dist-info/LICENCE.txt
mlaut-0.2.0.dist-info/METADATA
mlaut-0.2.0.dist-info/WHEEL
mlaut-0.2.0.dist-info/top_level.txt
mlaut-0.2.0.dist-info/RECORD
