Metadata-Version: 2.1
Name: mlaut
Version: 0.2.0
Summary: Automation of large-scale training, evaluation and benchmarking of machine learning algorithms.
Home-page: https://alan-turing-institute.github.io/mlaut/
Author: Viktor Kazakov
Author-email: viktor.kazakov.18@ucl.ac.uk
License: BDS
Platform: UNKNOWN
Requires-Dist: numpy
Requires-Dist: h5py
Requires-Dist: pandas
Requires-Dist: scikit-learn
Requires-Dist: scikit-posthocs
Requires-Dist: scipy
Requires-Dist: tables
Requires-Dist: tensorflow
Requires-Dist: Orange3
Requires-Dist: matplotlib
Requires-Dist: wrapt
